[{"inputs":[],"stateMutability":"nonpayable","type":"constructor"},{"anonymous":false,"inputs":[{"indexed":false,"internalType":"string","name":"circleId","type":"string"},{"indexed":false,"internalType":"string","name":"applicantDID","type":"string"}],"name":"ApplicationApproved","type":"event"},{"anonymous":false,"inputs":[{"indexed":false,"internalType":"string","name":"circleId","type":"string"},{"indexed":false,"internalType":"string","name":"applicantDID","type":"string"}],"name":"ApplicationRejected","type":"event"},{"anonymous":false,"inputs":[{"indexed":false,"internalType":"string","name":"circleId","type":"string"},{"indexed":false,"internalType":"string","name":"applicantDID","type":"string"}],"name":"ApplicationSubmitted","type":"event"},{"anonymous":false,"inputs":[{"indexed":false,"internalType":"string","name":"circleId","type":"string"},{"indexed":false,"internalType":"string","name":"ownerDID","type":"string"},{"indexed":false,"internalType":"string","name":"ownerOrgName","type":"string"}],"name":"CircleCreated","type":"event"},{"anonymous":false,"inputs":[{"indexed":false,"internalType":"string","name":"circleId","type":"string"},{"indexed":false,"internalType":"string","name":"memberDID","type":"string"}],"name":"MemberLeft","type":"event"},{"anonymous":false,"inputs":[{"indexed":false,"internalType":"string","name":"circleId","type":"string"},{"indexed":false,"internalType":"string","name":"newOwnerDID","type":"string"}],"name":"OwnershipTransferred","type":"event"},{"anonymous":false,"inputs":[{"indexed":false,"internalType":"uint256","name":"productId","type":"uint256"}],"name":"ProductApproved","type":"event"},{"anonymous":false,"inputs":[{"indexed":false,"internalType":"uint256","name":"productId","type":"uint256"},{"indexed":false,"internalType":"string","name":"circleId","type":"string"},{"indexed":false,"internalType":"string","name":"ownerDID","type":"string"}],"name":"ProductCreated","type":"event"},{"anonymous":false,"inputs":[{"indexed":false,"internalType":"uint256","name":"productId","type":"uint256"}],"name":"ProductEdited","type":"event"},{"anonymous":false,"inputs":[{"indexed":false,"internalType":"uint256","name":"productId","type":"uint256"},{"indexed":false,"internalType":"bool","name":"onShelf","type":"bool"}],"name":"ProductShelfStatusChanged","type":"event"},{"inputs":[],"name":"admin","outputs":[{"internalType":"address","name":"","type":"address"}],"stateMutability":"view","type":"function"},{"inputs":[{"internalType":"string","name":"circleId","type":"string"},{"internalType":"string","name":"applicantDID","type":"string"},{"internalType":"string","name":"orgName","type":"string"},{"internalType":"string","name":"socialCreditCode","type":"string"}],"name":"applyToJoinCircle","outputs":[],"stateMutability":"nonpayable","type":"function"},{"inputs":[{"internalType":"string","name":"circleId","type":"string"},{"internalType":"string","name":"ownerDID","type":"string"},{"internalType":"string","name":"applicantDID","type":"string"}],"name":"approveApplication","outputs":[],"stateMutability":"nonpayable","type":"function"},{"inputs":[{"internalType":"string","name":"circleId","type":"string"},{"internalType":"string","name":"ownerDID","type":"string"},{"internalType":"uint256","name":"productId","type":"uint256"}],"name":"approveProduct","outputs":[],"stateMutability":"nonpayable","type":"function"},{"inputs":[{"internalType":"string","name":"circleId","type":"string"},{"internalType":"string","name":"name","type":"string"},{"internalType":"string","name":"ownerDID","type":"string"},{"internalType":"string","name":"ownerOrgName","type":"string"}],"name":"createCircle","outputs":[],"stateMutability":"nonpayable","type":"function"},{"inputs":[{"internalType":"string","name":"circleId","type":"string"},{"internalType":"string","name":"memberDID","type":"string"},{"internalType":"string","name":"name","type":"string"},{"internalType":"string","name":"price","type":"string"},{"internalType":"enum CircleStructs.ProductType","name":"productType","type":"uint8"},{"internalType":"string","name":"ipfsHash","type":"string"}],"name":"createProduct","outputs":[],"stateMutability":"nonpayable","type":"function"},{"inputs":[{"internalType":"uint256","name":"productId","type":"uint256"},{"internalType":"string","name":"memberDID","type":"string"},{"internalType":"string","name":"newName","type":"string"},{"internalType":"string","name":"newPrice","type":"string"},{"internalType":"string","name":"newIpfsHash","type":"string"}],"name":"editProduct","outputs":[],"stateMutability":"nonpayable","type":"function"},{"inputs":[{"internalType":"string","name":"circleId","type":"string"},{"internalType":"string","name":"memberDID","type":"string"}],"name":"exitCircle","outputs":[],"stateMutability":"nonpayable","type":"function"},{"inputs":[{"internalType":"uint256","name":"page","type":"uint256"},{"internalType":"uint256","name":"pageSize","type":"uint256"}],"name":"getAllCircleIds","outputs":[{"internalType":"string","name":"","type":"string"}],"stateMutability":"view","type":"function"},{"inputs":[{"internalType":"uint256","name":"page","type":"uint256"},{"internalType":"uint256","name":"pageSize","type":"uint256"}],"name":"getAllCircles","outputs":[{"internalType":"string","name":"","type":"string"}],"stateMutability":"view","type":"function"},{"inputs":[{"internalType":"uint256","name":"page","type":"uint256"},{"internalType":"uint256","name":"pageSize","type":"uint256"}],"name":"getAllProducts","outputs":[{"internalType":"string","name":"","type":"string"}],"stateMutability":"view","type":"function"},{"inputs":[{"internalType":"string","name":"circleId","type":"string"},{"internalType":"uint256","name":"page","type":"uint256"},{"internalType":"uint256","name":"pageSize","type":"uint256"}],"name":"getApplications","outputs":[{"internalType":"string","name":"","type":"string"}],"stateMutability":"view","type":"function"},{"inputs":[{"internalType":"string","name":"circleId","type":"string"},{"internalType":"uint256","name":"page","type":"uint256"},{"internalType":"uint256","name":"pageSize","type":"uint256"}],"name":"getCircleMembers","outputs":[{"internalType":"string","name":"","type":"string"}],"stateMutability":"view","type":"function"},{"inputs":[{"internalType":"string","name":"circleId","type":"string"},{"internalType":"uint256","name":"page","type":"uint256"},{"internalType":"uint256","name":"pageSize","type":"uint256"}],"name":"getMembersInCircleForAdmin","outputs":[{"internalType":"string","name":"","type":"string"}],"stateMutability":"view","type":"function"},{"inputs":[{"internalType":"uint256","name":"productId","type":"uint256"}],"name":"getProductById","outputs":[{"components":[{"internalType":"uint256","name":"id","type":"uint256"},{"internalType":"string","name":"name","type":"string"},{"internalType":"string","name":"price","type":"string"},{"internalType":"enum CircleStructs.ProductType","name":"productType","type":"uint8"},{"internalType":"bool","name":"onShelf","type":"bool"},{"internalType":"string","name":"ipfsHash","type":"string"},{"internalType":"enum CircleStructs.AuditStatus","name":"auditStatus","type":"uint8"},{"internalType":"string","name":"ownerDID","type":"string"},{"internalType":"string","name":"circleId","type":"string"}],"internalType":"struct CircleStructs.Product","name":"","type":"tuple"}],"stateMutability":"view","type":"function"},{"inputs":[{"internalType":"string","name":"circleId","type":"string"},{"internalType":"string","name":"ownerDID","type":"string"},{"internalType":"string","name":"applicantDID","type":"string"}],"name":"rejectApplication","outputs":[],"stateMutability":"nonpayable","type":"function"},{"inputs":[{"internalType":"uint256","name":"productId","type":"uint256"},{"internalType":"string","name":"memberDID","type":"string"},{"internalType":"bool","name":"onShelf","type":"bool"}],"name":"setProductOnShelf","outputs":[],"stateMutability":"nonpayable","type":"function"},{"inputs":[{"internalType":"string","name":"circleId","type":"string"},{"internalType":"string","name":"currentOwnerDID","type":"string"},{"internalType":"string","name":"newOwnerDID","type":"string"},{"internalType":"string","name":"newOwnerOrgName","type":"string"}],"name":"transferCircleOwnership","outputs":[],"stateMutability":"nonpayable","type":"function"}]
